odoo/addons/sale_coupon_partner/README.rst
odoo/addons/sale_coupon_partner/__init__.py
odoo/addons/sale_coupon_partner/__manifest__.py
odoo/addons/sale_coupon_partner/i18n/it.po
odoo/addons/sale_coupon_partner/i18n/sale_coupon_partner.pot
odoo/addons/sale_coupon_partner/models/__init__.py
odoo/addons/sale_coupon_partner/models/sale_coupon_program.py
odoo/addons/sale_coupon_partner/readme/CONTRIBUTORS.rst
odoo/addons/sale_coupon_partner/readme/DESCRIPTION.rst
odoo/addons/sale_coupon_partner/reports/__init__.py
odoo/addons/sale_coupon_partner/reports/sale_report.py
odoo/addons/sale_coupon_partner/reports/sale_report_views.xml
odoo/addons/sale_coupon_partner/static/description/icon.png
odoo/addons/sale_coupon_partner/static/description/index.html
odoo/addons/sale_coupon_partner/tests/__init__.py
odoo/addons/sale_coupon_partner/tests/test_sale_coupon_partner.py
odoo/addons/sale_coupon_partner/views/sale_coupon_program_views.xml
odoo14_addon_sale_coupon_partner-14.0.1.0.1.dev7.dist-info/METADATA
odoo14_addon_sale_coupon_partner-14.0.1.0.1.dev7.dist-info/WHEEL
odoo14_addon_sale_coupon_partner-14.0.1.0.1.dev7.dist-info/top_level.txt
odoo14_addon_sale_coupon_partner-14.0.1.0.1.dev7.dist-info/RECORD
